MANIFEST.in
README
changelog.txt
darc.py
license.txt
setup.py
Darc.egg-info/PKG-INFO
Darc.egg-info/SOURCES.txt
Darc.egg-info/dependency_links.txt
Darc.egg-info/top_level.txt
demo/test/test.gif