Metadata-Version: 1.0
Name: Darc
Version: 1.2.1
Summary: Darc is an archiving system for use in media projects that allows developers to contain and use their data files from .darc files that store data in a bz2 compressed and AES encrypted (optional) format.
Home-page: https://github.com/Nekroze/Darc/wiki
Author: Taylor "Nekroze" Lawson
Author-email: nekroze@eturnilnetwork.com
License: LGPL
Download-URL: http://pypi.python.org/pypi/Darc/
Platform: win32
Platform: unix
Classifier: Development Status :: 4 - Beta
Classifier: Intended Audience :: Developers
Classifier: License :: OSI Approved :: GNU Library or Lesser General Public License (LGPL)
Classifier: Operating System :: Microsoft
Classifier: Operating System :: POSIX
Classifier: Programming Language :: Python :: 2 :: Only
Classifier: Topic :: Games/Entertainment
Classifier: Topic :: Multimedia
Classifier: Topic :: Security :: Cryptography
Classifier: Topic :: Software Development :: Libraries :: Python Modules
Classifier: Topic :: System :: Archiving
